[{"cost": "167", "path": [{"origin": "MDW", "destination": "CUN", "time_depart": "2023-12-24 13:12", "time_arrive": "2023-12-24 18:00", "airline": "FFT"}]}, {"cost": "288", "path": [{"origin": "MDW", "destination": "DEN", "time_depart": "2023-12-24 07:45", "time_arrive": "2023-12-24 09:34", "airline": "FFT"}, {"origin": "DEN", "destination": "CUN", "time_depart": "2023-12-24 12:07", "time_arrive": "2023-12-24 18:21", "airline": "FFT"}]}, {"cost": "338", "path": [{"origin": "MDW", "destination": "PHL", "time_depart": "2023-12-24 12:31", "time_arrive": "2023-12-24 15:26", "airline": "FFT"}, {"origin": "PHL", "destination": "CUN", "time_depart": "2023-12-25 09:00", "time_arrive": "2023-12-25 13:26", "airline": "FFT"}]}, {"cost": "298", "path": [{"origin": "MDW", "destination": "MCO", "time_depart": "2023-12-24 13:24", "time_arrive": "2023-12-24 17:09", "airline": "FFT"}, {"origin": "MCO", "destination": "CUN", "time_depart": "2023-12-25 11:45", "time_arrive": "2023-12-25 14:15", "airline": "FFT"}]}, {"cost": "298", "path": [{"origin": "MDW", "destination": "MCO", "time_depart": "2023-12-24 17:22", "time_arrive": "2023-12-24 21:07", "airline": "FFT"}, {"origin": "MCO", "destination": "CUN", "time_depart": "2023-12-25 11:45", "time_arrive": "2023-12-25 14:15", "airline": "FFT"}]}]